{
    "data": {
        "url": "04 - data.json"
    },
    "mark": {
        "type": "bar"
    },
    "encoding": {
        "x": {
            "field": "IMDB_Rating",
            "type": "quantitative",
            "bin": {
                "maxbins": 20
            }
        },
        "y": {
            "field": "Rotten_Tomatoes_Rating",
            "type": "quantitative",
            "bin": {
                "maxbins": 10
            }
        },
        "color": {
            "type": "quantitative",
            "aggregate": "count"
        }
    },
    "width": 300,
    "height": 150
}